odoo/addons/account_invoice_margin_sale/README.rst
odoo/addons/account_invoice_margin_sale/__init__.py
odoo/addons/account_invoice_margin_sale/__manifest__.py
odoo/addons/account_invoice_margin_sale/i18n/account_invoice_margin_sale.pot
odoo/addons/account_invoice_margin_sale/i18n/es.po
odoo/addons/account_invoice_margin_sale/i18n/fr_FR.po
odoo/addons/account_invoice_margin_sale/i18n/it.po
odoo/addons/account_invoice_margin_sale/models/__init__.py
odoo/addons/account_invoice_margin_sale/models/account_invoice.py
odoo/addons/account_invoice_margin_sale/models/sale.py
odoo/addons/account_invoice_margin_sale/readme/CONTRIBUTORS.md
odoo/addons/account_invoice_margin_sale/readme/DESCRIPTION.md
odoo/addons/account_invoice_margin_sale/readme/INSTALL.md
odoo/addons/account_invoice_margin_sale/readme/USAGE.md
odoo/addons/account_invoice_margin_sale/static/description/icon.png
odoo/addons/account_invoice_margin_sale/static/description/index.html
odoo/addons/account_invoice_margin_sale/tests/__init__.py
odoo/addons/account_invoice_margin_sale/tests/test_account_invoice_margin_sale.py
odoo_addon_account_invoice_margin_sale-18.0.1.0.0.2.dist-info/METADATA
odoo_addon_account_invoice_margin_sale-18.0.1.0.0.2.dist-info/WHEEL
odoo_addon_account_invoice_margin_sale-18.0.1.0.0.2.dist-info/top_level.txt
odoo_addon_account_invoice_margin_sale-18.0.1.0.0.2.dist-info/RECORD
